Metadata-Version: 2.3
Name: nsa-pythonik
Version: 1.15.0
Summary: Python SDK for Iconik's API
License: MIT
Keywords: iconik,api,sdk,media
Author: brant
Author-email: brant@northshoreautomation.com
Requires-Python: >=3.9,<4.0
Classifier: Development Status :: 4 - Beta
Classifier: Intended Audience :: Developers
Classifier: License :: OSI Approved :: MIT License
Classifier: Programming Language :: Python :: 3
Classifier: Programming Language :: Python :: 3.9
Classifier: Programming Language :: Python :: 3.10
Classifier: Programming Language :: Python :: 3.11
Classifier: Programming Language :: Python :: 3.12
Classifier: Programming Language :: Python :: 3.13
Classifier: Topic :: Software Development :: Libraries :: Python Modules
Requires-Dist: loguru (>=0.7.2,<0.8.0)
Requires-Dist: pydantic (>=2.4.2,<3.0.0)
Requires-Dist: requests (>=2.31.0,<3.0.0)
Requires-Dist: requests-mock (>=1.11.0,<2.0.0)
Project-URL: Homepage, https://github.com/NorthShoreAutomation/pythonik
Project-URL: Repository, https://github.com/NorthShoreAutomation/pythonik
